TNKDEV/__init__.py
TNKDEV/__version__.py
TNKDEV/info.py
TNKDEV-1.0.5.dist-info/METADATA
TNKDEV-1.0.5.dist-info/WHEEL
TNKDEV-1.0.5.dist-info/top_level.txt
TNKDEV-1.0.5.dist-info/RECORD
