Metadata-Version: 2.1
Name: TNKDEV
Version: 1.0.5
Summary: Đây Là Contact Của TNKDEV
Home-page: https://github.com/tnk-admin/TNKDEV
Author: K07VN
Author-email: khanhnekyh2007@gmail.com
Keywords: python,GAUTRICKER,KHANH,TNKDEV,TNK,K07VN,GAU,TRUONGNGOCKHANH
Classifier: License :: OSI Approved :: GNU General Public License v3 (GPLv3)
Classifier: Programming Language :: Python :: 3.7
Classifier: Programming Language :: Python :: 3.8
Classifier: Programming Language :: Python :: 3.9
Classifier: Programming Language :: Python :: 3.10
Classifier: Programming Language :: Python :: 3.11
Classifier: Programming Language :: Python :: 3.12
Classifier: License :: OSI Approved :: MIT License
Classifier: Operating System :: OS Independent
Requires-Python: >=3.6
Requires-Dist: pycryptodome
